{
"meta":{"test_sets":[],"test_metrics":[],"learn_metrics":[{"best_value":"Min","name":"Logloss"}],"launch_mode":"Train","parameters":"","iteration_count":100,"learn_sets":["learn"],"name":"experiment"},
"iterations":[
{"learn":[0.5603995004],"iteration":0,"passed_time":0.002720731762,"remaining_time":0.2693524444},
{"learn":[0.4776897903],"iteration":1,"passed_time":0.005526922934,"remaining_time":0.2708192237},
{"learn":[0.4111919859],"iteration":2,"passed_time":0.01034092546,"remaining_time":0.33435659},
{"learn":[0.3609791614],"iteration":3,"passed_time":0.0133943432,"remaining_time":0.3214642367},
{"learn":[0.3268631674],"iteration":4,"passed_time":0.01660211487,"remaining_time":0.3154401826},
{"learn":[0.2957181105],"iteration":5,"passed_time":0.01965501463,"remaining_time":0.3079285625},
{"learn":[0.2667711987],"iteration":6,"passed_time":0.02349185464,"remaining_time":0.3121060688},
{"learn":[0.248261316],"iteration":7,"passed_time":0.02657326402,"remaining_time":0.3055925363},
{"learn":[0.2326862252],"iteration":8,"passed_time":0.02940771777,"remaining_time":0.2973447019},
{"learn":[0.2139481481],"iteration":9,"passed_time":0.03215152886,"remaining_time":0.2893637597},
{"learn":[0.1992526048],"iteration":10,"passed_time":0.03492217146,"remaining_time":0.2825521145},
{"learn":[0.1896194608],"iteration":11,"passed_time":0.03803875167,"remaining_time":0.2789508456},
{"learn":[0.1842399777],"iteration":12,"passed_time":0.04271121207,"remaining_time":0.2858365731},
{"learn":[0.1769868971],"iteration":13,"passed_time":0.04621654578,"remaining_time":0.2839016384},
{"learn":[0.1680179184],"iteration":14,"passed_time":0.04904099643,"remaining_time":0.2778989798},
{"learn":[0.1617025443],"iteration":15,"passed_time":0.05151240801,"remaining_time":0.2704401421},
{"learn":[0.1560983827],"iteration":16,"passed_time":0.05433061471,"remaining_time":0.2652612365},
{"learn":[0.1499560003],"iteration":17,"passed_time":0.05891225877,"remaining_time":0.2683780677},
{"learn":[0.1462663794],"iteration":18,"passed_time":0.06134100208,"remaining_time":0.2615063773},
{"learn":[0.1428781488],"iteration":19,"passed_time":0.06391335423,"remaining_time":0.2556534169},
{"learn":[0.1396116316],"iteration":20,"passed_time":0.06615950533,"remaining_time":0.2488857582},
{"learn":[0.1369772788],"iteration":21,"passed_time":0.06829170563,"remaining_time":0.2421251382},
{"learn":[0.1333786493],"iteration":22,"passed_time":0.07151546863,"remaining_time":0.2394213515},
{"learn":[0.1289616906],"iteration":23,"passed_time":0.07437363735,"remaining_time":0.2355165183},
{"learn":[0.1267187221],"iteration":24,"passed_time":0.07710361977,"remaining_time":0.2313108593},
{"learn":[0.1240880164],"iteration":25,"passed_time":0.07942396589,"remaining_time":0.226052826},
{"learn":[0.1216385382],"iteration":26,"passed_time":0.08163473298,"remaining_time":0.2207161299},
{"learn":[0.1209206087],"iteration":27,"passed_time":0.08374725794,"remaining_time":0.2153500918},
{"learn":[0.1163250949],"iteration":28,"passed_time":0.0863329351,"remaining_time":0.2113668411},
{"learn":[0.1147761816],"iteration":29,"passed_time":0.0889318144,"remaining_time":0.2075075669},
{"learn":[0.1132875919],"iteration":30,"passed_time":0.09119608171,"remaining_time":0.202984827},
{"learn":[0.1105128432],"iteration":31,"passed_time":0.09348161129,"remaining_time":0.198648424},
{"learn":[0.1073587844],"iteration":32,"passed_time":0.09566889353,"remaining_time":0.1942368444},
{"learn":[0.1050614488],"iteration":33,"passed_time":0.0980441401,"remaining_time":0.1903209778},
{"learn":[0.1027957055],"iteration":34,"passed_time":0.1002866819,"remaining_time":0.1862466949},
{"learn":[0.1009007326],"iteration":35,"passed_time":0.1030838017,"remaining_time":0.1832600919},
{"learn":[0.100360185],"iteration":36,"passed_time":0.1057722447,"remaining_time":0.1800986869},
{"learn":[0.09738640832],"iteration":37,"passed_time":0.1078952734,"remaining_time":0.1760396566},
{"learn":[0.09650469009],"iteration":38,"passed_time":0.1101664129,"remaining_time":0.1723115689},
{"learn":[0.0957717869],"iteration":39,"passed_time":0.1125046503,"remaining_time":0.1687569755},
{"learn":[0.09396788138],"iteration":40,"passed_time":0.1145839326,"remaining_time":0.1648890738},
{"learn":[0.09294463293],"iteration":41,"passed_time":0.1170344102,"remaining_time":0.1616189474},
{"learn":[0.09193438316],"iteration":42,"passed_time":0.1198965126,"remaining_time":0.1589325864},
{"learn":[0.08999668535],"iteration":43,"passed_time":0.122516797,"remaining_time":0.1559304689},
{"learn":[0.08902178963],"iteration":44,"passed_time":0.1248403348,"remaining_time":0.1525826314},
{"learn":[0.08813145608],"iteration":45,"passed_time":0.1269374941,"remaining_time":0.14901358},
{"learn":[0.08746269158],"iteration":46,"passed_time":0.1291301541,"remaining_time":0.1456148546},
{"learn":[0.08643019451],"iteration":47,"passed_time":0.1313937901,"remaining_time":0.1423432726},
{"learn":[0.08532655676],"iteration":48,"passed_time":0.1338798935,"remaining_time":0.1393443789},
{"learn":[0.08427480897],"iteration":49,"passed_time":0.1366904725,"remaining_time":0.1366904725},
{"learn":[0.08344193168],"iteration":50,"passed_time":0.1389675772,"remaining_time":0.1335178683},
{"learn":[0.0827920908],"iteration":51,"passed_time":0.1410509665,"remaining_time":0.1302008921},
{"learn":[0.08248071049],"iteration":52,"passed_time":0.1435254985,"remaining_time":0.1272773289},
{"learn":[0.08157618266],"iteration":53,"passed_time":0.1459092468,"remaining_time":0.1242930621},
{"learn":[0.08092374099],"iteration":54,"passed_time":0.1480671228,"remaining_time":0.1211458277},
{"learn":[0.07963165356],"iteration":55,"passed_time":0.1506773199,"remaining_time":0.1183893228},
{"learn":[0.07879684607],"iteration":56,"passed_time":0.1533331212,"remaining_time":0.1156723546},
{"learn":[0.07782775133],"iteration":57,"passed_time":0.1555094169,"remaining_time":0.1126102674},
{"learn":[0.07698552789],"iteration":58,"passed_time":0.1577067956,"remaining_time":0.109592858},
{"learn":[0.07648600162],"iteration":59,"passed_time":0.1599550564,"remaining_time":0.1066367043},
{"learn":[0.0761394652],"iteration":60,"passed_time":0.1620929228,"remaining_time":0.1036331801},
{"learn":[0.07562014721],"iteration":61,"passed_time":0.164276438,"remaining_time":0.1006855588},
{"learn":[0.07461525196],"iteration":62,"passed_time":0.1670983479,"remaining_time":0.09813712494},
{"learn":[0.07410781817],"iteration":63,"passed_time":0.169618663,"remaining_time":0.09541049793},
{"learn":[0.07362759371],"iteration":64,"passed_time":0.1718716029,"remaining_time":0.09254624774},
{"learn":[0.07322856318],"iteration":65,"passed_time":0.1739730645,"remaining_time":0.08962248779},
{"learn":[0.07304841038],"iteration":66,"passed_time":0.176079267,"remaining_time":0.0867256091},
{"learn":[0.0725114078],"iteration":67,"passed_time":0.1781888013,"remaining_time":0.08385355354},
{"learn":[0.07104083424],"iteration":68,"passed_time":0.180469887,"remaining_time":0.08108067387},
{"learn":[0.07024403058],"iteration":69,"passed_time":0.1830426794,"remaining_time":0.07844686261},
{"learn":[0.06972386951],"iteration":70,"passed_time":0.1857611256,"remaining_time":0.07587426259},
{"learn":[0.06945260709],"iteration":71,"passed_time":0.1880455277,"remaining_time":0.07312881631},
{"learn":[0.06880307872],"iteration":72,"passed_time":0.1902329784,"remaining_time":0.07036014268},
{"learn":[0.06798936761],"iteration":73,"passed_time":0.1922436228,"remaining_time":0.06754505664},
{"learn":[0.06764395716],"iteration":74,"passed_time":0.1942791666,"remaining_time":0.06475972218},
{"learn":[0.06716708386],"iteration":75,"passed_time":0.1964455999,"remaining_time":0.06203545259},
{"learn":[0.06657036786],"iteration":76,"passed_time":0.1992567003,"remaining_time":0.05951823516},
{"learn":[0.06636811504],"iteration":77,"passed_time":0.2014558327,"remaining_time":0.05682087588},
{"learn":[0.0659228127],"iteration":78,"passed_time":0.2035535807,"remaining_time":0.05410917968},
{"learn":[0.06526211794],"iteration":79,"passed_time":0.2057296923,"remaining_time":0.05143242308},
{"learn":[0.06429727489],"iteration":80,"passed_time":0.2078366858,"remaining_time":0.04875181519},
{"learn":[0.06366907528],"iteration":81,"passed_time":0.2109849018,"remaining_time":0.04631375892},
{"learn":[0.06315569447],"iteration":82,"passed_time":0.2143582753,"remaining_time":0.04390470698},
{"learn":[0.06281577609],"iteration":83,"passed_time":0.2165522291,"remaining_time":0.04124804365},
{"learn":[0.06243996861],"iteration":84,"passed_time":0.2186988087,"remaining_time":0.03859390741},
{"learn":[0.06210286563],"iteration":85,"passed_time":0.2211161747,"remaining_time":0.03599565634},
{"learn":[0.06164932098],"iteration":86,"passed_time":0.2233615425,"remaining_time":0.03337586268},
{"learn":[0.06126631085],"iteration":87,"passed_time":0.2262870128,"remaining_time":0.03085731992},
{"learn":[0.06073753982],"iteration":88,"passed_time":0.2290171715,"remaining_time":0.0283054931},
{"learn":[0.06052580452],"iteration":89,"passed_time":0.2313109487,"remaining_time":0.02570121653},
{"learn":[0.06037072514],"iteration":90,"passed_time":0.2334241137,"remaining_time":0.02308590135},
{"learn":[0.05997042432],"iteration":91,"passed_time":0.2355506957,"remaining_time":0.02048266919},
{"learn":[0.05985786597],"iteration":92,"passed_time":0.237501991,"remaining_time":0.01787649395},
{"learn":[0.05954876665],"iteration":93,"passed_time":0.2397437478,"remaining_time":0.01530279241},
{"learn":[0.05941387118],"iteration":94,"passed_time":0.242454146,"remaining_time":0.01276074453},
{"learn":[0.05929319465],"iteration":95,"passed_time":0.2446120551,"remaining_time":0.01019216896},
{"learn":[0.05910694916],"iteration":96,"passed_time":0.2472153048,"remaining_time":0.00764583417},
{"learn":[0.05879192472],"iteration":97,"passed_time":0.2499998343,"remaining_time":0.005102037434},
{"learn":[0.05863016032],"iteration":98,"passed_time":0.2520920995,"remaining_time":0.002546384843},
{"learn":[0.05775629704],"iteration":99,"passed_time":0.254277724,"remaining_time":0}
]}